GyaoDL/__init__.py
GyaoDL/__main__.py
GyaoDL/gyaodl.py
GyaoDL-0.0.2.dist-info/LICENSE
GyaoDL-0.0.2.dist-info/LICENSE_JP
GyaoDL-0.0.2.dist-info/METADATA
GyaoDL-0.0.2.dist-info/WHEEL
GyaoDL-0.0.2.dist-info/top_level.txt
GyaoDL-0.0.2.dist-info/RECORD
