Metadata-Version: 2.1
Name: GyaoDL
Version: 0.0.2
Summary: This is a script to download videos from GYAO!
Home-page: https://github.com/xpadev-net/gyaodl
Author: xpadev-net
Author-email: xpadev@gmail.com
License: MIT
Keywords: GYAO!,yahoo,Download,Movie,OnDemand
Platform: UNKNOWN
Classifier: Development Status :: 4 - Beta
Classifier: License :: OSI Approved :: MIT License
Classifier: Programming Language :: Python
Classifier: Programming Language :: Python :: 3
Classifier: Programming Language :: Python :: 3.4
Classifier: Programming Language :: Python :: 3.5
Classifier: Programming Language :: Python :: 3.6
Classifier: Topic :: Multimedia :: Video :: Capture
Classifier: Topic :: Software Development :: Libraries :: Python Modules
License-File: LICENSE
License-File: LICENSE_JP
